Metadata-Version: 1.0
Name: distributions-functions
Version: 1.2
Summary: Gaussian and Binomial distributions
Home-page: UNKNOWN
Author: Sombit Bose
Author-email: sombit.bose15@gmail.com
License: UNKNOWN
Platform: UNKNOWN
